{
  "details": {},
  "highlights": [],
  "cases": [
    {
      "title": "TransUnion LLC v. Ramirez",
      "term": "2020-10",
      "number": "20-297",
      "argument": "2021-03-30",
      "decision": "2021-06-25",
      "transcript": true,
      "audio": 2,
      "files": 37
    },
    {
      "title": "Travelers Indemnity Co. v. Bailey",
      "term": "2008-10",
      "number": "08-295,08-307",
      "argument": "2009-03-30",
      "decision": "2009-06-18",
      "transcript": true,
      "audio": 1
    }
  ]
}
